[
  {
    "id": "a5cfbc5b-4779-47f6-be39-de9938b84630",
    "name": "Calvin Howell MD",
    "phone": "825.463.9707 x7288",
    "email": "Erica.Purdy22@hotmail.com",
    "job": "Lead Accountability Officer"
  },
  {
    "id": "4874122b-777e-4819-90a0-427a2e7fd619",
    "name": "Maxine Douglas",
    "phone": "1-639-963-2943 x5025",
    "email": "Josefina_Wehner-Thiel49@yahoo.com",
    "job": "Investor Accounts Agent"
  },
  {
    "id": "02adad97-05a8-474a-8dee-5dbdb4b3ba31",
    "name": "Tim West",
    "phone": "525-207-8831",
    "email": "Brittany3@hotmail.com",
    "job": "Principal Security Administrator"
  },
  {
    "id": "0f715ea6-e966-4660-9b31-2d6b54fab650",
    "name": "Doreen Ortiz Sr.",
    "phone": "(425) 688-6137 x69705",
    "email": "Emmalee_Crona70@gmail.com",
    "job": "Corporate Group Analyst"
  },
  {
    "id": "b9323bba-b5ad-4a1d-9db7-3f1984971b94",
    "name": "Miss Cassandra Homenick",
    "phone": "1-245-902-0202 x86506",
    "email": "Trisha39@gmail.com",
    "job": "Internal Applications Analyst"
  },
  {
    "id": "f57317a1-8ed5-4d8c-b4fd-243617c2c73b",
    "name": "Preston Parisian",
    "phone": "589-404-9857 x9193",
    "email": "Georgianna.Bernier@gmail.com",
    "job": "Forward Directives Technician"
  },
  {
    "id": "82bc764e-ea56-45d9-9995-48ff239402d6",
    "name": "Rebecca Pacocha",
    "phone": "1-219-897-1283 x90680",
    "email": "Abel92@yahoo.com",
    "job": "Internal Identity Developer"
  },
  {
    "id": "19797ea4-a562-4f38-9ce5-e3612d9b589c",
    "name": "Alicia Volkman III",
    "phone": "1-650-264-0572 x6887",
    "email": "Katarina_Rempel@hotmail.com",
    "job": "Direct Response Representative"
  },
  {
    "id": "e86f67a5-eb05-4388-ad83-e9566e401467",
    "name": "Floyd Ebert",
    "phone": "238-976-8359 x442",
    "email": "Angus_Hand@hotmail.com",
    "job": "Principal Creative Designer"
  },
  {
    "id": "3e80d20c-ba30-431d-98f9-644433898879",
    "name": "Jacquelyn Baumbach",
    "phone": "(355) 674-1242",
    "email": "Gabrielle99@hotmail.com",
    "job": "Corporate Factors Facilitator"
  },
  {
    "id": "b66804f3-cbe1-4ab3-89dd-844ed23ea41c",
    "name": "Traci Altenwerth",
    "phone": "407.620.7203 x361",
    "email": "Henriette21@hotmail.com",
    "job": "Future Metrics Agent"
  },
  {
    "id": "b923883c-8937-42fc-8ade-4bdede71c49d",
    "name": "Calvin Murphy",
    "phone": "969.638.2375",
    "email": "Dixie.Halvorson19@gmail.com",
    "job": "Chief Directives Manager"
  },
  {
    "id": "ddb89b7c-0864-4c63-9476-4e753945b0bf",
    "name": "Carlton Nitzsche",
    "phone": "(209) 677-4199",
    "email": "Francesca.Little@gmail.com",
    "job": "National Factors Engineer"
  },
  {
    "id": "33138639-8dc1-4618-a398-ec3625c0232e",
    "name": "Bert McLaughlin",
    "phone": "(351) 296-7616",
    "email": "Bertrand.Sanford93@yahoo.com",
    "job": "Central Data Planner"
  },
  {
    "id": "86209b4b-1b8c-4377-9ec0-d53aa848fca8",
    "name": "Vernon Schuster",
    "phone": "773.220.9870 x96519",
    "email": "Crawford_Wehner@yahoo.com",
    "job": "Senior Branding Assistant"
  },
  {
    "id": "3515d420-b980-419e-8ea4-06c3aa941cfc",
    "name": "Megan Leffler",
    "phone": "383.849.7799 x74813",
    "email": "Marisa_Bartoletti43@hotmail.com",
    "job": "Human Marketing Officer"
  },
  {
    "id": "b12ece30-5928-431a-80c0-45d54b06223e",
    "name": "Nancy Marquardt",
    "phone": "517-931-4425 x9954",
    "email": "Hollis41@hotmail.com",
    "job": "Global Paradigm Supervisor"
  }
]